{
    "0": {
        "color": "green", 
        "points": 3, 
        "0": {
            "x": 20, 
            "y": 30
        }, 
        "1": {
            "x": 50, 
            "y": 10
        }, 
        "2": {
            "x": 80, 
            "y": 240
        }
    }, 
    "1": {
        "color": "teal", 
        "points": 3, 
        "0": {
            "x": 70, 
            "y": 75
        }, 
        "1": {
            "x": 100, 
            "y": 125
        }, 
        "2": {
            "x": 200, 
            "y": 300
        }
    }
}